{
  "product_recommendations": [
    {
      "id": 1,
      "product_name": "깨끗한도시 두루마리 휴지 30개 X 1박스",
      "consumer_price": 75000,
      "product_price": 50000,
      "view_status": true
    },
    {
      "id": 2,
      "product_name": "더블유 세안용품 5종 세트",
      "consumer_price": 148000,
      "product_price": 128000,
      "view_status": true
    },
    {
      "id": 3,
      "product_name": "그린라이프 5종 칫솔 8개입 세트",
      "consumer_price": 10890,
      "product_price": 6900,
      "view_status": false
    },
    {
      "id": 4,
      "product_name": "미세모 우드 칫솔 2종 24개입",
      "consumer_price": 75000,
      "product_price": 50000,
      "view_status": true
    },
    {
      "id": 5,
      "product_name": "뱀부 트윈 물결칫솔 120개입",
      "consumer_price": 119000,
      "product_price": 88000,
      "view_status": false
    },
    {
      "id": 6,
      "product_name": "켄트 오리지널 치약 120g 10개",
      "consumer_price": 33000,
      "product_price": 28900,
      "view_status": true
    },
    {
      "id": 7,
      "product_name": "메디안 치석케어 오리지널 치약, 120g 9개",
      "consumer_price": 35700,
      "product_price": 13650,
      "view_status": false
    },
    {
      "id": 8,
      "product_name": "송월타월 호텔수건 크러쉬 150g 30수 면사 5개입",
      "consumer_price": 17000,
      "product_price": 17000,
      "view_status": false
    },
    {
      "id": 9,
      "product_name": "송월타월 호텔수건 크러쉬 150g 30수 면사, 10개입",
      "consumer_price": 34000,
      "product_price": 29700,
      "view_status": true
    },
    {
      "id": 10,
      "product_name": "JMW 에어젯 울트라 항공모터 헤어 드라이기 1650W, MS6031E",
      "consumer_price": 92000,
      "product_price": 75200,
      "view_status": false
    }
  ]
}
